NeteaseCloudMusic/NeteaseCloudMusicApi.js
NeteaseCloudMusic/__init__.py
NeteaseCloudMusic/config.json
NeteaseCloudMusic/help.py
NeteaseCloudMusic/main.py
NeteaseCloudMusicApi-0.1.2.dist-info/LICENSE
NeteaseCloudMusicApi-0.1.2.dist-info/METADATA
NeteaseCloudMusicApi-0.1.2.dist-info/WHEEL
NeteaseCloudMusicApi-0.1.2.dist-info/top_level.txt
NeteaseCloudMusicApi-0.1.2.dist-info/RECORD
