Metadata-Version: 2.1
Name: NeteaseCloudMusicApi
Version: 0.1.2
Summary: 网易云音乐API NeteaseCloudMusicApi项目的 Python SDK
Home-page: https://github.com/me/myproject
Author: Awesome Soul
Author-email: me@example.com
License: MIT
Classifier: License :: OSI Approved :: MIT License
Classifier: Programming Language :: Python
Classifier: Programming Language :: Python :: 3
Classifier: Programming Language :: Python :: 3.6
Classifier: Programming Language :: Python :: Implementation :: CPython
Classifier: Programming Language :: Python :: Implementation :: PyPy
Requires-Python: >=3.6.0
License-File: LICENSE
Requires-Dist: py-mini-racer
Requires-Dist: requests
